llama_index/readers/uniprot/__init__.py
llama_index/readers/uniprot/base.py
llama_index_readers_uniprot-0.2.1.dist-info/METADATA
llama_index_readers_uniprot-0.2.1.dist-info/WHEEL
llama_index_readers_uniprot-0.2.1.dist-info/RECORD
