Metadata-Version: 2.4
Name: llama-index-readers-uniprot
Version: 0.2.1
Summary: UniProt reader for LlamaIndex
Author-email: Evgenii Neumerzhitckii <sausageskin@gmail.com>
License-Expression: MIT
Keywords: bioinformatics,llama-index,uniprot
Classifier: Development Status :: 3 - Alpha
Classifier: Intended Audience :: Science/Research
Classifier: License :: OSI Approved :: MIT License
Classifier: Programming Language :: Python :: 3
Classifier: Programming Language :: Python :: 3.8
Classifier: Programming Language :: Python :: 3.9
Classifier: Programming Language :: Python :: 3.10
Classifier: Programming Language :: Python :: 3.11
Requires-Python: <4.0,>=3.9
Requires-Dist: llama-index-core<0.15,>=0.13.0
